app_pack_generator/__init__.py
app_pack_generator/application.py
app_pack_generator/cwl.py
app_pack_generator/descriptor.py
app_pack_generator/docker.py
app_pack_generator/git.py
app_pack_generator/util.py
app_pack_generator/version.py
app_pack_generator/schemas/nbformat.v4.0.schema.json
app_pack_generator/schemas/nbformat.v4.1.schema.json
app_pack_generator/schemas/nbformat.v4.2.schema.json
app_pack_generator/schemas/nbformat.v4.3.schema.json
app_pack_generator/schemas/nbformat.v4.4.schema.json
app_pack_generator/schemas/nbformat.v4.5.schema.json
app_pack_generator/templates/Dockerfile
app_pack_generator/templates/app_desc.json
app_pack_generator/templates/process.cwl
app_pack_generator/templates/stage_in.cwl
app_pack_generator/templates/stage_out.cwl
app_pack_generator/templates/workflow.cwl
app_pack_generator-1.1.0.dist-info/licenses/LICENSE
test/conftest.py
test/test_docker.py
test/test_git.py
app_pack_generator-1.1.0.dist-info/METADATA
app_pack_generator-1.1.0.dist-info/WHEEL
app_pack_generator-1.1.0.dist-info/top_level.txt
app_pack_generator-1.1.0.dist-info/RECORD
