Metadata-Version: 2.4
Name: app_pack_generator
Version: 1.1.0
Summary: Generates an OGC application package from a Jupyter Notebook by parsing its it's papermill parameterized metadata.
Author: James McDuffie, Max Zhan
License: MIT License
Keywords: unity-sds,ogc,packaging,cwl,jupyter
Classifier: Development Status :: 4 - Beta
Classifier: Environment :: Console
Classifier: Intended Audience :: Developers
Classifier: License :: OSI Approved :: MIT License
Classifier: Natural Language :: English
Classifier: Operating System :: OS Independent
Classifier: Programming Language :: Python :: 3 :: Only
Classifier: Topic :: Software Development :: Build Tools
Classifier: Topic :: Utilities
Requires-Python: >=3.9
License-File: LICENSE
Requires-Dist: papermill>=2.4.0
Requires-Dist: GitPython>=3.1.30
Requires-Dist: docker>=6.0.1
Requires-Dist: jsonschema>=4.17.3
Requires-Dist: jupyter-repo2docker>=2022.10.0
Requires-Dist: giturlparse>=0.10.0
Requires-Dist: tabulate>=0.9.0
Dynamic: license-file
